alu.v
module alu (
    input  [7:0] OPERAND1,
    OPERAND2,
    input  [2:0] ALUOP,
    input        carry_flag,
    carry_use,
    output       carry_out,
    zero_out,
    output [7:0] ALURESULT
);


  // intermediary wires for operations.
  wire [7:0] SUM, SBB, ROT_LEFT, ROT_RIGHT;
  wire [7:0] logicAND, logicOR, logicXOR, logicNOR;
  wire carry_sum, borrow_diff, l_carry, r_carry;

  // intermediary wires for rotating
  wire RL_carry_status, RL_last_bit, RR_carry_status, RR_first_bit;
  wire [6:0] RL_main, RR_main;

  // if ROL: carry flag is as it is. if RLC: MSB becomes carry flag
  assign RL_carry_status = (carry_flag && !carry_use) || (OPERAND1[7] && carry_use);
  // if ROR: carry flag is as it is. if RRC: LSB becomes carry flag
  assign RR_carry_status = (carry_flag && !carry_use) || (OPERAND1[0] && carry_use);

  // main block in ROL/RLC and ROR/RRC that is simply rotated with no conflict
  assign RL_main = OPERAND1[6:0];
  assign RR_main = OPERAND1[7:1];

  // if ROL: LSB is MSB. if RLC: LSB is carry
  assign RL_last_bit = (OPERAND1[7] && !carry_use) || (carry_flag && carry_use);
  // if ROR: MSB is LSB. if RRC: MSB is carry
  assign RR_first_bit = (OPERAND1[0] && !carry_use) || (carry_flag && carry_use);

  assign {carry_sum, SUM} = OPERAND1 + OPERAND2 + {7'b0000000, carry_flag && carry_use};
  assign {borrow_diff, SBB} = OPERAND1 + OPERAND2 - {7'b0000000, carry_flag};

  assign {l_carry, ROT_LEFT} = {RL_carry_status, RL_main, RL_last_bit};
  assign {r_carry, ROT_RIGHT} = {RR_carry_status, RR_first_bit, RR_main};

  assign logicAND = OPERAND1 & OPERAND2;
  assign logicOR = OPERAND1 | OPERAND2;
  assign logicXOR = OPERAND1 ^ OPERAND2;
  assign logicNOR = ~(logicOR);

  // ALUOP definitions and usage
  // 00: simple and gate
  // 01: simple or gate
  // 02: simple xor gate
  // 03: simple nor gate
  // 04: add instruction for ADD, ADC, SUB
  // 05: SBB instruction specifically
  // 06: ROL and RLC based on carry_use
  // 07: ROR and RRC based on carry_use
  assign ALURESULT            =
                                (ALUOP == 3'o0) ? logicAND:
                                (ALUOP == 3'o1) ? logicOR:
                                (ALUOP == 3'o2) ? logicXOR:
                                (ALUOP == 3'o3) ? logicNOR:
                                (ALUOP == 3'o4) ? SUM:
                                (ALUOP == 3'o5) ? SBB:
                                (ALUOP == 3'o6) ? ROT_LEFT:
                                (ALUOP == 3'o7) ? ROT_RIGHT : 8'h00;

  assign carry_out            =
                                (ALUOP == 3'o4) ? carry_sum
                                : (ALUOP == 3'o5) ? borrow_diff
                                : (ALUOP == 3'o6) ? l_carry
                                : (ALUOP == 3'o7) ? r_carry : carry_flag;

  assign zero_out = (ALURESULT == 8'h00);
endmodule

mux_4x1.v
module mux_4x1 (
    input  [7:0] a,
    b,
    c,
    d,
    input  [1:0] s,
    output [7:0] z
);

  assign z = (s == 2'b00) ? a : (s == 2'b01) ? b : (s == 2'b10) ? c : (s == 2'b11) ? d : 1'bz;

endmodule

mux_2x1.v
module mux_2x1 (
  input [7:0]  x, y,
	input s,
  output [7:0] z
  );

  assign z =
    (s == 1'b0)
      ? x
      : (s == 1'b1)
        ? y
        : 1'bz;

endmodule

twos_comp.v
module twos_comp (
  input [7:0] x,
  output [7:0] y
);

  assign y = ~x + 1'b1;

endmodule

register_file.v
module register_file (
  input CLK,
  input [2:0] READREG1, READREG2, WRITEREG,
  input WRITEENABLE,
  input [7:0] WRITEDATA,
  output reg [7:0] REGOUT1, REGOUT2
);

  reg [7:0] regs [0:7];
  integer i;

  initial begin
    for (i = 0; i < 8; i = i + 1) begin
      regs[i] = 8'h00;
    end
    regs[6] = 8'h01;
  end

  always @(posedge CLK) begin
    if (WRITEENABLE) begin
      regs[WRITEREG] <= WRITEDATA;
    end
  end

  always @(*) begin
    REGOUT1 = regs[READREG1];
    REGOUT2 = regs[READREG2];
  end

endmodule

inst_memory.v
module inst_memory (
    input [7:0] PC,
    input CLK,
    input reg WRITE_STACK_ENABLE,
    input reg [7:0] stack_value,
    input reg [7:0] stack_pointer,
    output [7:0] inst
);

  reg [7:0] mem[0:255];
  integer i;

  initial begin
    for (i = 0; i < 256; i = i + 1) begin
      mem[i] = 8'hFF;
    end

    mem[0] = 8'hC0;  // MOV A, DB
    mem[1] = 8'h2F;  // 2FH as DB
    mem[2] = 8'h3F;  // RLC
    mem[3] = 8'h1E;  // SUB A, DB
    mem[4] = 8'h55;  // DB = 55H
    mem[5] = 8'hC8;  // MOV B, A
    mem[6] = 8'hC0;  // MOV A, DB
    mem[7] = 8'h78;  // DB = 78
    mem[8] = 8'hEE;  // RST

  end

  always @(posedge CLK) begin
    if (WRITE_STACK_ENABLE) begin
      mem[stack_pointer] = stack_value;
    end
  end

  assign inst = mem[PC];
endmodule

cu.v
// refer to cpu_architecture.md for more info.
// it will simply not be possible to include everything here
module cu (
    input CLK,

    input      [7:0] inst,
    output reg [7:0] PC,
    output reg       WRITE_STACK_ENABLE,
    output reg [7:0] stack_value,
    stack_pointer,

    output reg       carry_flag,
    carry_use,
    input  reg       carry_in,
    zero_in,
    output reg [2:0] ALUOP,

    output reg [7:0] IMMEDIATE,
    output reg [2:0] READREG1,
    READREG2,
    WRITEREG,
    output reg       WRITEENABLE,

    output reg       MUX1_SEL,
    MUX2_SEL,
    output reg [1:0] MUX3_SEL
);


  // All instructions are present at cpu_architecture.md
  // I've also made a google sheet to keep track of what instruction
  // is mapped to which hex code.

  reg [1:0] state;
  reg immediate_flag, zero_flag;
  reg jmp_enable, call_enable, ret_enable;

  parameter FETCH = 2'b00;
  parameter DECODE = 2'b01;
  parameter EXECUTE = 2'b10;
  parameter FETCH_IMMEDIATE = 2'b11;

  initial begin
    reset();
  end

  // helper function for resetting to start
  task reset();
    begin
      state              = FETCH;
      PC                 = 8'h00;
      immediate_flag     = 1'b0;
      WRITEENABLE        = 1'b0;
      carry_flag         = 1'b0;
      carry_use          = 1'b0;
      zero_flag          = 1'b0;
      MUX1_SEL           = 1'b0;
      MUX2_SEL           = 1'b0;
      MUX3_SEL           = 2'b00;
      jmp_enable         = 1'b0;
      call_enable        = 1'b0;
      ret_enable         = 1'b0;
      stack_pointer      = 8'hFF;
      WRITE_STACK_ENABLE = 1'b0;
      READREG1           = 3'b000;
      READREG2           = 3'b000;
    end
  endtask

  // helper function for branching instructions
  task branch_logic(input flag);
    begin
      if ((flag && inst[0]) || (!flag && !inst[0])) begin
        state          <= FETCH_IMMEDIATE;
        PC             <= PC + 1;
        immediate_flag <= 1'b1;
        if (inst[3]) begin
          call_enable <= 1'b1;
        end else begin
          jmp_enable <= 1'b1;
        end
      end else begin
        state <= FETCH;
        PC    <= PC + 2;
      end
    end
  endtask

  // helper function for return instructions
  task return_logic(input flag);
    begin
      state <= EXECUTE;

      if ((flag && inst[0]) || (!flag && !inst[0])) begin
        stack_pointer <= stack_pointer + 1;
        ret_enable    <= 1'b1;
      end else begin
        PC <= PC + 1;
      end
    end
  endtask

  // 3 states: 1 for fetching instruction
  // 2nd for decoding and sending proper control signals.
  // since mux's and alu are combinational, they won't need additional
  // cycle.
  // and we can get the output of alu, store it in register bank,
  // and simultaneously fetch next instruction as well.

  always @(posedge CLK) begin
    case (state)
      FETCH: begin
        state              <= DECODE;
        WRITE_STACK_ENABLE <= 1'b0;
        WRITEENABLE        <= 1'b0;

        // no operation in these op codes
        if (
	      (inst == 8'h07 || inst == 8'h47 || inst == 8'h87)
	      || (inst == 8'h11 || inst == 8'h16 || inst == 8'h17)
	      || (inst[7:3] == 5'b00100)
	      || (inst[7:3] == 5'b00110)
	      || (inst[7:3] == 5'b01001)
	      || (inst[7:4] == 4'b0101)
	      || (inst[7:5] == 3'b011)
	      || (inst[7:3] == 5'b10001)
	      || (inst[7:4] == 4'b1001)
	      || (inst == 8'hA1 || inst == 8'hA6 || inst == 8'hA7 || inst[7:3] == 5'b10101)
	      || (inst[7:4] == 4'b1011)
	      || (inst == 8'hDE || inst == 8'hDF || inst == 8'hE6 || inst == 8'hE7)
	      || (inst == 8'hF1 || inst == 8'hF6 || inst == 8'hF7)
	      || (inst == 8'hF9 || inst == 8'hFE || inst == 8'hFF)
	      ) begin
          state <= FETCH;
          PC    <= PC + 1;
        end
      end

      DECODE: begin
        // aiming for serial op codes, based on category.

        // but first, two special op codes: reset (RST) and freeze (FRZ)
        if (inst == 8'hEE) begin
          $display("reset");
          reset();
        end else if (inst == 8'hEF) begin
          $display("cpu frozen for reading reg value");
        end  // logical operations: AND OR NOR condition: 00/01/10 000 xxx
        else if (inst[7:6] != 2'b11 && inst[5:3] == 3'b000) begin
          $display("AND, OR, XOR");
          READREG1 <= 3'b000;
          WRITEREG <= 3'b000;
          WRITEENABLE <= 1'b1;
          // alu op code will be 000 for AND, 001 for OR, 010 for XOR
          ALUOP    <= {1'b0, inst[7:6]};
          MUX1_SEL <= 1'b0;
          MUX3_SEL <= 2'b00;

          // xx 000 110 is op code for immediate operation
          if (inst[2:1] == 2'b11) begin
            MUX2_SEL       <= 1'b1;
            immediate_flag <= 1'b1;
            PC             <= PC + 1;
            state          <= FETCH_IMMEDIATE;
          end  // if not immediate operation:
          else begin
            MUX2_SEL <= 1'b0;
            READREG2 <= inst[2:0];
            state    <= EXECUTE;
          end
        end  // logical operation NOR is quite complex
             // (C6/7 H, CE/F H) and (D6/7 H)
        // two conditions: (1100 x11x) and (1101 011x) respectively
        else if ((inst[7:4] == 4'b1100 && inst[2:1] == 2'b11) || (inst[7:1] == 7'b1101011)) begin
          $display("NOR");
          READREG1 <= 3'b000;
          // reg 2 logic:
          // bit 4, 3, 0 decide the register
          // example: NOR A, C = CE H = 1100 1110
          // bit 4 3 0: 010 -> C register
          READREG2 <= {inst[4:3], inst[0]};
          WRITEREG <= 3'b000;
          WRITEENABLE <= 1'b1;

          MUX1_SEL <= 1'b0;
          MUX2_SEL <= 1'b0;
          MUX3_SEL <= 2'b00;

          ALUOP <= 3'b011;  // NOR opcode for alu: 011
          state <= EXECUTE;
        end  // rotate operations
             // 2E -> ROL, 2F -> ROR (no carry usage in both): 0010 111x
        // 3E -> RLC, 3F -> RRC (carry usage in both): 0011 111x
        // we can treat ROL, RLC as same ALU instruction with carry usage differing
        // we can treat ROR, RRC as same ALU instruction with carry usage differing
        else if (inst[7:5] == 3'b001 && inst[3:1] == 3'b111) begin
          $display("Rotate");
          READREG1    <= 3'b000;
          WRITEREG    <= 3'b000;
          WRITEENABLE <= 1'b1;

          ALUOP       <= {2'b11, (inst[0] == 1'b1)};  // 110 to rotate left, 111 to rotate right
          carry_use   <= inst[4] == 1'b1;
          MUX1_SEL    <= 1'b0;
          MUX2_SEL    <= 1'b0;
          MUX3_SEL    <= 2'b00;

          state       <= EXECUTE;
        end  // arithmetic operations op codes: 00 xx1 xxx
        else if (inst[7:6] == 2'b00 && inst[3] == 1'b1) begin
          $display("arithmetic");
          WRITEENABLE <= inst[2:0] != 3'b110;
          carry_use <= inst[2:0] == 3'b111;

          // readreg1 will be A, unless for increment/decrement
          // if inc/dec then we'd have to have respective regsiter
          READREG1 <= inst[5] == 1'b1 ? inst[2:0] : 3'b000;

          // reg 2 logic: if add, sub normal logic
          // if incrementing, decrementing,
          // we use special registr at reg[6] that has default value of 01.
          // if ADC or SBB, then we need only B
          READREG2 <= (inst[5] == 1'b1) ? 3'b110 : (inst[2:0] == 3'b111) ? 3'b001 : inst[2:0];

          // if INC/DEC operation, use given register, else use A register.
          WRITEREG <= inst[5] == 1'b1 ? inst[2:0] : 3'b000;

          // if subtracting or decreasing, then we'd want its 2's complement.
          MUX1_SEL <= inst[4] == 1'b1;
          MUX2_SEL <= inst[2:0] == 3'b110;
          MUX3_SEL <= inst[2:0] == 3'b110 ? 2'b10 : 00;

          // if ADD A, DB or SUB B, DB, fetch immediate
          state <= inst[2:0] == 3'b110 ? FETCH_IMMEDIATE : EXECUTE;
          PC <= inst[2:0] == 3'b110 ? PC + 1 : PC;
          immediate_flag <= inst[2:0] == 3'b110;
          ALUOP <= inst == 8'h1F ? 3'b101 : 3'b100;
        end  // return operations, at op code: 1010 xxx
        else if (inst[7:3] == 5'b00010) begin
          $display("return");
          // unconditional return
          if (inst[2:0] === 3'b000) begin
            state         <= FETCH;
            PC            <= stack_value;
            stack_pointer <= stack_pointer + 1;
          end  // conditional returns
          else if (inst[2:1] == 2'b01) begin
            return_logic(carry_flag);
          end else if (inst[2:1] == 2'b10) begin
            return_logic(zero_flag);
          end
        end

	      // JMP/CALL instruction at F0-F5H and F8-FDH, simple take the next byte in inst_memory and go there.
                    // in the form of 1111 0xxx for jmp, 1xxx for call
        else if (inst[7:4] == 4'b1111) begin
          $display("branch");
          // simple JMP (F0H) or CALL (F8H)
          if (inst[2:0] == 3'b000) begin
            state          <= FETCH_IMMEDIATE;
            immediate_flag <= 1'b1;
            PC             <= PC + 1;

            if (inst[3] == 0) begin
              jmp_enable <= 1'b1;
            end else begin
              call_enable <= 1'b1;
            end
          end else if (inst[2:1] == 2'b01) begin
            branch_logic(zero_flag);
          end else if (inst[2:1] == 2'b10) begin
            branch_logic(carry_flag);
          end
        end  // data transfer operation: 11 xxx xxx
        else if (inst[7:6] == 2'b11) begin
          $display("data transfer");
          WRITEENABLE <= inst[5:3] != inst[2:0];
          READREG1 <= inst[2:0];
          WRITEREG <= inst[5:3];

          MUX3_SEL <= 2'b01;

          state <= EXECUTE;

          if (inst[5:3] == inst[2:0]) begin
            immediate_flag <= 1'b1;
            MUX3_SEL       <= 2'b10;
            PC             <= PC + 1;
            state          <= FETCH_IMMEDIATE;
          end
        end
      end

      FETCH_IMMEDIATE: begin
        IMMEDIATE      <= inst;
        immediate_flag <= 1'b0;
        state          <= EXECUTE;
        WRITEENABLE    <= !jmp_enable;
      end

      EXECUTE: begin
        WRITEENABLE <= 1'b0;
        PC <= (jmp_enable || call_enable) ? IMMEDIATE : PC + 1;
        WRITE_STACK_ENABLE <= jmp_enable;

        if (call_enable) begin
          stack_value   <= PC + 8'h01;
          stack_pointer <= stack_pointer - 8'h01;
        end

        if (ret_enable) begin
          PC <= stack_value;
        end

        jmp_enable <= 1'b0;
        call_enable <= 1'b0;
        ret_enable <= 1'b0;
        zero_flag <= (inst[7:6] == 2'b00 && inst[3] == 1'b1) && !(inst == 8'h2E || inst == 8'h2F || inst == 8'h3E || inst == 8'h3F)
          ? zero_in
          : zero_flag;
        carry_flag <= (inst[7:3] == 5'b00011)  // if SUB, ! CY
        ? !carry_in
					: ((!jmp_enable && !call_enable) && (inst[7:3] == 5'b00001 || inst[7:1] == 7'b0010111 || inst[7:1] == 7'b0011111)) // if ROTATE/ADD then carry_in
        ? carry_in : carry_flag;

        state <= FETCH;
      end

      default: begin
        state <= FETCH;
      end
    endcase
  end

endmodule

cpu.v
`timescale 1ns / 1ps
module cpu ();
  reg CLK;
  wire [7:0] PC;
  wire [7:0] inst;
  wire [2:0] READREG1, READREG2, WRITEREG;
  wire [7:0] REGOUT1, REGOUT2, COMP_OUT;
  wire WRITEENABLE;
  wire MUX1_SEL, MUX2_SEL;
  wire [1:0] MUX3_SEL;
  wire [7:0] MUX2_OUT, OPERAND2;
  wire [7:0] IMMEDIATE, ALURESULT;
  wire [2:0] ALUOP;
  wire carry_flag, carry_use;
  wire carry, zero_out;
  wire WRITE_STACK_ENABLE;
  wire [7:0] stack_value, stack_pointer;
  wire [7:0] WRITEDATA;
  wire [7:0] R0, R1, R2, R3, R4, R5, R6, R7;

  cu cu (
      .inst(inst),
      .CLK(CLK),
      .READREG1(READREG1),
      .READREG2(READREG2),
      .WRITEREG(WRITEREG),
      .WRITEENABLE(WRITEENABLE),
      .MUX1_SEL(MUX1_SEL),
      .MUX2_SEL(MUX2_SEL),
      .MUX3_SEL(MUX3_SEL),
      .carry_in(carry),
      .carry_flag(carry_flag),
      .carry_use(carry_use),
      .zero_in(zero_out),
      .WRITE_STACK_ENABLE(WRITE_STACK_ENABLE),
      .IMMEDIATE(IMMEDIATE),
      .PC(PC),
      .stack_value(stack_value),
      .stack_pointer(stack_pointer),
      .ALUOP(ALUOP)
  );

  inst_memory mem (
      .PC(PC),
      .CLK(CLK),
      .WRITE_STACK_ENABLE(WRITE_STACK_ENABLE),
      .stack_value(stack_value),
      .stack_pointer(stack_pointer),
      .inst(inst)
  );

  register_file register_file (
      .CLK        (CLK),
      .READREG1   (READREG1),
      .READREG2   (READREG2),
      .WRITEREG   (WRITEREG),
      .WRITEENABLE(WRITEENABLE),
      .WRITEDATA  (WRITEDATA),
      .REGOUT1    (REGOUT1),
      .REGOUT2    (REGOUT2)
  );

  assign R0 = register_file.regs[0];
  assign R1 = register_file.regs[1];
  assign R2 = register_file.regs[2];
  assign R3 = register_file.regs[3];
  assign R4 = register_file.regs[4];
  assign R5 = register_file.regs[5];
  assign R6 = register_file.regs[6];
  assign R7 = register_file.regs[7];

  mux_2x1 m2 (
      .x(REGOUT2),
      .y(IMMEDIATE),
      .s(MUX2_SEL),
      .z(MUX2_OUT)
  );

  twos_comp twos_comp (
      .x(MUX2_OUT),
      .y(COMP_OUT)
  );

  mux_2x1 m1 (
      .x(MUX2_OUT),
      .y(COMP_OUT),
      .s(MUX1_SEL),
      .z(OPERAND2)
  );

  mux_4x1 m3 (
      .a(ALURESULT),
      .b(REGOUT1),
      .c(IMMEDIATE),
      .s(MUX3_SEL),
      .z(WRITEDATA)
  );

  alu alu (
      .OPERAND1(REGOUT1),
      .OPERAND2(OPERAND2),
      .ALUOP(ALUOP),
      .carry_flag(carry_flag),
      .carry_out(carry),
      .carry_use(carry_use),
      .zero_out(zero_out),
      .ALURESULT(ALURESULT)
  );

  always #5 CLK = ~CLK;

  initial begin
    $dumpfile("cpu.vcd");
    $dumpvars(0, cpu);

    CLK = 0;
    #1800;
    $finish;
  end
endmodule

cpu.vcd
$date
	Sun Jul 12 18:29:25 2026
$end
$version
	Icarus Verilog
$end
$timescale
	1ps
$end
$scope module cpu $end
$var wire 8 ! R0 [7:0] $end
$var wire 8 " R1 [7:0] $end
$var wire 8 # R2 [7:0] $end
$var wire 8 $ R3 [7:0] $end
$var wire 8 % R4 [7:0] $end
$var wire 8 & R5 [7:0] $end
$var wire 8 ' R6 [7:0] $end
$var wire 8 ( R7 [7:0] $end
$var wire 1 ) zero_out $end
$var wire 8 * stack_value [7:0] $end
$var wire 8 + stack_pointer [7:0] $end
$var wire 8 , inst [7:0] $end
$var wire 1 - carry_use $end
$var wire 1 . carry_flag $end
$var wire 1 / carry $end
$var wire 1 0 WRITE_STACK_ENABLE $end
$var wire 3 1 WRITEREG [2:0] $end
$var wire 1 2 WRITEENABLE $end
$var wire 8 3 WRITEDATA [7:0] $end
$var wire 8 4 REGOUT2 [7:0] $end
$var wire 8 5 REGOUT1 [7:0] $end
$var wire 3 6 READREG2 [2:0] $end
$var wire 3 7 READREG1 [2:0] $end
$var wire 8 8 PC [7:0] $end
$var wire 8 9 OPERAND2 [7:0] $end
$var wire 2 : MUX3_SEL [1:0] $end
$var wire 1 ; MUX2_SEL $end
$var wire 8 < MUX2_OUT [7:0] $end
$var wire 1 = MUX1_SEL $end
$var wire 8 > IMMEDIATE [7:0] $end
$var wire 8 ? COMP_OUT [7:0] $end
$var wire 8 @ ALURESULT [7:0] $end
$var wire 3 A ALUOP [2:0] $end
$var reg 1 B CLK $end
$scope module alu $end
$var wire 1 C RL_carry_status $end
$var wire 1 D RL_last_bit $end
$var wire 1 E RR_carry_status $end
$var wire 1 F RR_first_bit $end
$var wire 8 G logicAND [7:0] $end
$var wire 8 H logicNOR [7:0] $end
$var wire 8 I logicOR [7:0] $end
$var wire 8 J logicXOR [7:0] $end
$var wire 1 ) zero_out $end
$var wire 1 K r_carry $end
$var wire 1 L l_carry $end
$var wire 1 - carry_use $end
$var wire 1 M carry_sum $end
$var wire 1 / carry_out $end
$var wire 1 . carry_flag $end
$var wire 1 N borrow_diff $end
$var wire 8 O SUM [7:0] $end
$var wire 8 P SBB [7:0] $end
$var wire 7 Q RR_main [6:0] $end
$var wire 8 R ROT_RIGHT [7:0] $end
$var wire 8 S ROT_LEFT [7:0] $end
$var wire 7 T RL_main [6:0] $end
$var wire 8 U OPERAND2 [7:0] $end
$var wire 8 V OPERAND1 [7:0] $end
$var wire 8 W ALURESULT [7:0] $end
$var wire 3 X ALUOP [2:0] $end
$upscope $end
$scope module cu $end
$var wire 1 B CLK $end
$var wire 1 / carry_in $end
$var wire 1 ) zero_in $end
$var wire 8 Y inst [7:0] $end
$var parameter 2 Z DECODE $end
$var parameter 2 [ EXECUTE $end
$var parameter 2 \ FETCH $end
$var parameter 2 ] FETCH_IMMEDIATE $end
$var reg 3 ^ ALUOP [2:0] $end
$var reg 8 _ IMMEDIATE [7:0] $end
$var reg 1 = MUX1_SEL $end
$var reg 1 ; MUX2_SEL $end
$var reg 2 ` MUX3_SEL [1:0] $end
$var reg 8 a PC [7:0] $end
$var reg 3 b READREG1 [2:0] $end
$var reg 3 c READREG2 [2:0] $end
$var reg 1 2 WRITEENABLE $end
$var reg 3 d WRITEREG [2:0] $end
$var reg 1 0 WRITE_STACK_ENABLE $end
$var reg 1 e call_enable $end
$var reg 1 . carry_flag $end
$var reg 1 - carry_use $end
$var reg 1 f immediate_flag $end
$var reg 1 g jmp_enable $end
$var reg 1 h ret_enable $end
$var reg 8 i stack_pointer [7:0] $end
$var reg 8 j stack_value [7:0] $end
$var reg 2 k state [1:0] $end
$var reg 1 l zero_flag $end
$scope task branch_logic $end
$var reg 1 m flag $end
$upscope $end
$scope task reset $end
$upscope $end
$scope task return_logic $end
$var reg 1 n flag $end
$upscope $end
$upscope $end
$scope module m1 $end
$var wire 1 = s $end
$var wire 8 o z [7:0] $end
$var wire 8 p y [7:0] $end
$var wire 8 q x [7:0] $end
$upscope $end
$scope module m2 $end
$var wire 1 ; s $end
$var wire 8 r y [7:0] $end
$var wire 8 s z [7:0] $end
$var wire 8 t x [7:0] $end
$upscope $end
$scope module m3 $end
$var wire 8 u a [7:0] $end
$var wire 8 v c [7:0] $end
$var wire 8 w d [7:0] $end
$var wire 2 x s [1:0] $end
$var wire 8 y z [7:0] $end
$var wire 8 z b [7:0] $end
$upscope $end
$scope module mem $end
$var wire 1 B CLK $end
$var wire 8 { PC [7:0] $end
$var wire 1 0 WRITE_STACK_ENABLE $end
$var wire 8 | inst [7:0] $end
$var wire 8 } stack_pointer [7:0] $end
$var wire 8 ~ stack_value [7:0] $end
$var integer 32 !" i [31:0] $end
$upscope $end
$scope module register_file $end
$var wire 1 B CLK $end
$var wire 3 "" READREG1 [2:0] $end
$var wire 3 #" READREG2 [2:0] $end
$var wire 8 $" WRITEDATA [7:0] $end
$var wire 1 2 WRITEENABLE $end
$var wire 3 %" WRITEREG [2:0] $end
$var reg 8 &" REGOUT1 [7:0] $end
$var reg 8 '" REGOUT2 [7:0] $end
$var integer 32 (" i [31:0] $end
$upscope $end
$scope module twos_comp $end
$var wire 8 )" x [7:0] $end
$var wire 8 *" y [7:0] $end
$upscope $end
$upscope $end
$enddefinitions $end
$comment Show the parameter values. $end
$dumpall
b11 ]
b0 \
b10 [
b1 Z
$end
#0
$dumpvars
b0 *"
b0 )"
b1000 ("
b0 '"
b0 &"
bx %"
bx $"
b0 #"
b0 ""
b100000000 !"
bx ~
b11111111 }
b11000000 |
b0 {
b0 z
bx y
b0 x
bz w
bx v
bx u
b0 t
b0 s
bx r
b0 q
b0 p
b0 o
xn
xm
0l
b0 k
bx j
b11111111 i
0h
0g
0f
0e
bx d
b0 c
b0 b
b0 a
b0 `
bx _
bx ^
b11000000 Y
bx X
bx W
b0 V
b0 U
b0 T
b0 S
b0 R
b0 Q
b0 P
b0 O
0N
0M
0L
0K
b0 J
b0 I
b11111111 H
b0 G
0F
0E
0D
0C
0B
bx A
bx @
b0 ?
bx >
0=
b0 <
0;
b0 :
b0 9
b0 8
b0 7
b0 6
b0 5
b0 4
bx 3
02
bx 1
00
0/
0.
0-
b11000000 ,
b11111111 +
bx *
x)
b0 (
b1 '
b0 &
b0 %
b0 $
b0 #
b0 "
b0 !
$end
#5000
b1 k
1B
#10000
0B
#15000
b101111 ,
b101111 Y
b101111 |
bx 3
bx y
bx $"
b1 8
b1 a
b1 {
1f
b11 k
b10 :
b10 `
b10 x
b0 1
b0 d
b0 %"
1B
#20000
0B
#25000
b101111 3
b101111 y
b101111 $"
12
b10 k
0f
b101111 >
b101111 _
b101111 r
b101111 v
1B
#30000
0B
#35000
b101111 G
1F
b10010111 R
b1011110 S
b11010001 ?
b11010001 p
b11010001 *"
b101111 9
b101111 U
b101111 o
b1011110 P
b1011110 O
b11010000 H
b101111 <
b101111 q
b101111 s
b101111 )"
b10111 Q
b101111 T
b0 J
b101111 I
b101111 4
b101111 t
b101111 '"
b101111 5
b101111 V
b101111 z
b101111 &"
b111111 ,
b111111 Y
b111111 |
b101111 !
b0 k
b10 8
b10 a
b10 {
02
1B
#40000
0B
#45000
b1 k
1B
#50000
0B
#55000
1/
0)
b10111 R
1K
0F
1E
b10111 @
b10111 W
b10111 u
b10111 3
b10111 y
b10111 $"
b10 k
b0 :
b0 `
b0 x
1-
b111 A
b111 X
b111 ^
12
1B
#60000
0B
#65000
b10001011 3
b10001011 y
b10001011 $"
b10001011 @
b10001011 W
b10001011 u
b10001011 R
b101111 S
b11101001 ?
b11101001 p
b11101001 *"
b10111 9
b10111 U
b10111 o
b101101 P
b101111 O
b11101000 H
1F
1D
b10111 <
b10111 q
b10111 s
b10111 )"
b1011 Q
b10111 T
b0 J
b10111 I
b10111 G
b11110 ,
b11110 Y
b11110 |
b10111 4
b10111 t
b10111 '"
b10111 5
b10111 V
b10111 z
b10111 &"
b0 k
1.
b11 8
b11 a
b11 {
02
b10111 !
1B
#70000
0B
#75000
b1 k
1B
#80000
0B
#85000
0)
0N
b11101000 @
b11101000 W
b11101000 u
b11100111 P
0M
b101000 H
b11101000 O
b101110 S
1L
b11000110 J
b11010111 I
b10001 G
b11010001 ?
b11010001 p
b11010001 *"
b11010001 9
b11010001 U
b11010001 o
b101111 <
b101111 q
b101111 s
b101111 )"
1C
0D
0/
b1010101 ,
b1010101 Y
b1010101 |
b101111 3
b101111 y
b101111 $"
b1 4
b1 t
b1 '"
b100 A
b100 X
b100 ^
1f
b100 8
b100 a
b100 {
b11 k
b10 :
b10 `
b10 x
1;
1=
b110 6
b110 c
b110 #"
0-
1B
#90000
0B
#95000
b11000010 @
b11000010 W
b11000010 u
b11000001 P
b11000010 O
b1000000 H
b10111100 J
b10111111 I
b11 G
b10101011 9
b10101011 U
b10101011 o
b10101011 ?
b10101011 p
b10101011 *"
b1010101 3
b1010101 y
b1010101 $"
b1010101 <
b1010101 q
b1010101 s
b1010101 )"
12
b10 k
0f
b1010101 >
b1010101 _
b1010101 r
b1010101 v
1B
#100000
0B
#105000
1)
b0 @
b0 W
b0 u
1/
b10101010 R
b10101010 S
b11111111 P
b0 O
1M
b0 H
b101010 Q
b1010101 T
b11111110 J
b11111111 I
b1 G
b11001000 ,
b11001000 Y
b11001000 |
b1010101 5
b1010101 V
b1010101 z
b1010101 &"
b0 k
b101 8
b101 a
b101 {
02
b1010101 !
1B
#110000
0B
#115000
b1 k
1B
#120000
0B
#125000
b10 k
b1 :
b1 `
b1 x
b1 1
b1 d
b1 %"
12
1B
#130000
0B
#135000
b11000000 ,
b11000000 Y
b11000000 |
b1010101 "
b0 k
b110 8
b110 a
b110 {
02
1B
#140000
0B
#145000
b1 k
1B
#150000
0B
#155000
b1111000 ,
b1111000 Y
b1111000 |
b111 8
b111 a
b111 {
b10 :
b10 `
b10 x
1f
b11 k
b0 1
b0 d
b0 %"
1B
#160000
0B
#165000
0)
b11011101 @
b11011101 W
b11011101 u
0/
b11011100 P
b11011101 O
0M
b100010 H
b11011101 J
b11011101 I
b0 G
b10001000 9
b10001000 U
b10001000 o
b10001000 ?
b10001000 p
b10001000 *"
b1111000 3
b1111000 y
b1111000 $"
b1111000 <
b1111000 q
b1111000 s
b1111000 )"
12
b10 k
0f
b1111000 >
b1111000 _
b1111000 r
b1111000 v
1B
#170000
0B
#175000
1)
b0 @
b0 W
b0 u
1/
0F
b111100 R
b11110000 S
b11111111 P
b0 O
1M
b111 H
b111100 Q
b1111000 T
b11110000 J
b11111000 I
b1000 G
b1111000 5
b1111000 V
b1111000 z
b1111000 &"
b11101110 ,
b11101110 Y
b11101110 |
b1111000 !
b0 k
b1000 8
b1000 a
b1000 {
02
1B
#180000
0B
#185000
b1 k
1B
#190000
0B
#195000
0)
b11110000 @
b11110000 W
b11110000 u
0/
b11110000 O
0M
b10000111 H
0K
0L
b0 J
b1111000 I
b1111000 G
b11110000 P
0N
b1111000 9
b1111000 U
b1111000 o
0E
0C
b1111000 4
b1111000 t
b1111000 '"
b11110000 3
b11110000 y
b11110000 $"
b11000000 ,
b11000000 Y
b11000000 |
b0 6
b0 c
b0 #"
b0 :
b0 `
b0 x
0;
0=
0.
b0 8
b0 a
b0 {
b0 k
1B
#200000
0B
#205000
b1 k
1B
#210000
0B
#215000
b101111 ,
b101111 Y
b101111 |
b1111000 3
b1111000 y
b1111000 $"
b1 8
b1 a
b1 {
1f
b11 k
b10 :
b10 `
b10 x
1B
#220000
0B
#225000
b101111 3
b101111 y
b101111 $"
12
b10 k
0f
b101111 >
b101111 _
b101111 r
b101111 v
1B
#230000
0B
