twos_comp.v
module twos_comp (
  input [7:0] x,
  output [7:0] y
);

  assign y = ~x + 1'b1;

endmodule

twos_comp_tb.v
module twos_comp_tb;

  reg [7:0] x;
  wire [7:0] y;

  twos_comp uut (
    .x(x),
    .y(y)
  );

  initial begin
    $dumpfile("twos_comp.vcd");
    $dumpvars(0, uut);
    
    #10;
    x = 8'h00; #10;
    x = 8'h11; #10;
    x = 8'h43; #10;
    x = 8'h6A; #10;
    x = 8'h82; #10;
    x = 8'hAA; #10;
    x = 8'hCE; #10;
    x = 8'hEA; #10;
    $finish;
  end

endmodule

twos_comp.vcd
$date
	Tue Jun 30 08:10:36 2026
$end
$version
	Icarus Verilog
$end
$timescale
	1s
$end
$scope module twos_comp_tb $end
$scope module uut $end
$var wire 8 ! x [7:0] $end
$var wire 8 " y [7:0] $end
$upscope $end
$upscope $end
$enddefinitions $end
$comment Show the parameter values. $end
$dumpall
$end
#0
$dumpvars
bx "
bx !
$end
#10
b0 "
b0 !
#20
b11101111 "
b10001 !
#30
b10111101 "
b1000011 !
#40
b10010110 "
b1101010 !
#50
b1111110 "
b10000010 !
#60
b1010110 "
b10101010 !
#70
b110010 "
b11001110 !
#80
b10110 "
b11101010 !
